headersUpdate/__init__.py
headersUpdate/headers_update.py
UpdateUuid4-0.1.2.dist-info/METADATA
UpdateUuid4-0.1.2.dist-info/WHEEL
UpdateUuid4-0.1.2.dist-info/top_level.txt
UpdateUuid4-0.1.2.dist-info/RECORD
